discordbotpresence-0.6.7.data/data/LICENSE.md
http3/__init__.py
http3/__version__.py
http3/api.py
http3/auth.py
http3/client.py
http3/concurrency.py
http3/config.py
http3/decoders.py
http3/exceptions.py
http3/interfaces.py
http3/models.py
http3/multipart.py
http3/status_codes.py
http3/utils.py
http3/dispatch/__init__.py
http3/dispatch/asgi.py
http3/dispatch/connection.py
http3/dispatch/connection_pool.py
http3/dispatch/http11.py
http3/dispatch/http2.py
http3/dispatch/threaded.py
http3/dispatch/wsgi.py
discordbotpresence-0.6.7.dist-info/LICENSE.md
discordbotpresence-0.6.7.dist-info/METADATA
discordbotpresence-0.6.7.dist-info/WHEEL
discordbotpresence-0.6.7.dist-info/top_level.txt
discordbotpresence-0.6.7.dist-info/RECORD
