Metadata-Version: 2.1
Name: discordbotpresence
Version: 0.6.7
Summary: The next generation of discord bots
Home-page: https://github.com/CorwinDev/Discord-Bot
Author: Valky
Author-email: dreamer@gmail.com
License: BSD
Classifier: Development Status :: 3 - Alpha
Classifier: Environment :: Web Environment
Classifier: Intended Audience :: Developers
Classifier: License :: OSI Approved :: BSD License
Classifier: Operating System :: OS Independent
Classifier: Topic :: Internet :: WWW/HTTP
Classifier: Programming Language :: Python :: 3
Classifier: Programming Language :: Python :: 3.6
Classifier: Programming Language :: Python :: 3.7
Classifier: Programming Language :: Python :: 3.8
Requires-Python: >=3.11
License-File: LICENSE.md
Requires-Dist: certifi
Requires-Dist: chardet==3.*
Requires-Dist: h11==0.8.*
Requires-Dist: h2==3.*
Requires-Dist: idna==2.*
Requires-Dist: rfc3986==1.*
